su_master_mind_llm/__init__.py
su_master_mind_llm/__version__.py
su_master_mind_llm/plugin.py
su_master_mind_llm/resources.py
su_master_mind_llm-2026.1.26.dist-info/METADATA
su_master_mind_llm-2026.1.26.dist-info/WHEEL
su_master_mind_llm-2026.1.26.dist-info/entry_points.txt
su_master_mind_llm-2026.1.26.dist-info/RECORD
