Metadata-Version: 2.4
Name: su-master-mind-llm
Version: 2026.1.26
Summary: Sorbonne University Master MIND - Large Language Models course plugin
Author-email: Benjamin Piwowarski <benjamin@piwowarski.fr>
Requires-Python: >=3.10
Requires-Dist: accelerate>=1.12.0
Requires-Dist: auto-gptq>=0.7.0; sys_platform == 'linux'
Requires-Dist: autoawq>=0.2.0; sys_platform == 'linux'
Requires-Dist: bert-score>=0.3.13
Requires-Dist: bertviz>=1.4.1
Requires-Dist: codecarbon>=2.3.0
Requires-Dist: datasets>=4.4.1
Requires-Dist: evaluate>=0.4.6
Requires-Dist: gensim>=4.4.0
Requires-Dist: ipywidgets>=8.1.8
Requires-Dist: ir-datasets>=0.5.0
Requires-Dist: ir-measures>=0.4.3
Requires-Dist: outlines>=1.2.9
Requires-Dist: peft>=0.13.2
Requires-Dist: pillow>=10.0.0
Requires-Dist: pyterrier>=1
Requires-Dist: requests>=2.31.0
Requires-Dist: rouge-score>=0.1.2
Requires-Dist: sae-lens>=4.0.0
Requires-Dist: scikit-learn>=1.7.2
Requires-Dist: seaborn>=0.13.2
Requires-Dist: sentence-transformers>=3.0.0
Requires-Dist: su-master-mind[deep]<2026.8.1,>=2026.1.25.4
Requires-Dist: transformer-lens>=2.0.0
Requires-Dist: transformers>=4.56.1
